setup.py
django_pushall/__init__.py
django_pushall/admin.py
django_pushall/api.py
django_pushall/app_settings.py
django_pushall/apps.py
django_pushall/models.py
django_pushall/tests.py
django_pushall/urls.py
django_pushall/views.py
django_pushall.egg-info/PKG-INFO
django_pushall.egg-info/SOURCES.txt
django_pushall.egg-info/dependency_links.txt
django_pushall.egg-info/requires.txt
django_pushall.egg-info/top_level.txt
django_pushall/migrations/0001_initial.py
django_pushall/migrations/__init__.py