Metadata-Version: 1.1
Name: django-pushall
Version: 1.0.2b1
Summary: Django app for Pushall notice system
Home-page: https://github.com/forkhammer/django-pushall
Author: Forkhammer
Author-email: forkhammer@gmail.com
License: MIT License: https://github.com/forkhammer/django-pushall/blob/master/LICENSE
Platform: UNKNOWN
Classifier: Development Status :: 4 - Beta
Classifier: Environment :: Web Environment
Classifier: Framework :: Django
Classifier: Intended Audience :: Developers
Classifier: License :: OSI Approved :: MIT License
Classifier: Operating System :: OS Independent
Classifier: Programming Language :: Python
